{"1": {"iter": 150, "epoch": 1, "start_epoch": 0, "best_score": 0.17813, "best_iter": 150, "best_epoch": 1, "TrainLoss": 14.389949798583984, "CAPTrainLoss": 7.923959732055664, "SVOTrainLoss": 5.388324737548828, "mixer_from": -1, "scb_captions": 0, "Loss": -4.642, "Bleu_1": 0.69088, "Bleu_2": 0.53641, "Bleu_3": 0.42356, "Bleu_4": 0.27562, "METEOR": 0.24276, "ROUGE_L": 0.60121, "CIDEr": 0.17813, "SPICE": 0.02819}, "2": {"iter": 300, "epoch": 2, "start_epoch": 0, "best_score": 0.24967, "best_iter": 300, "best_epoch": 2, "TrainLoss": 12.138321876525879, "CAPTrainLoss": 5.943953990936279, "SVOTrainLoss": 5.161972999572754, "mixer_from": -1, "scb_captions": 0, "Loss": -4.574, "Bleu_1": 0.72727, "Bleu_2": 0.57609, "Bleu_3": 0.4818, "Bleu_4": 0.36677, "METEOR": 0.24227, "ROUGE_L": 0.61411, "CIDEr": 0.24967, "SPICE": 0.02739}, "3": {"iter": 450, "epoch": 3, "start_epoch": 0, "best_score": 0.30455, "best_iter": 450, "best_epoch": 3, "TrainLoss": 11.235173225402832, "CAPTrainLoss": 5.006313323974609, "SVOTrainLoss": 5.19071626663208, "mixer_from": -1, "scb_captions": 0, "Loss": -4.406, "Bleu_1": 0.72105, "Bleu_2": 0.56625, "Bleu_3": 0.46497, "Bleu_4": 0.35571, "METEOR": 0.26825, "ROUGE_L": 0.65125, "CIDEr": 0.30455, "SPICE": 0.03138}, "4": {"iter": 600, "epoch": 4, "start_epoch": 0, "best_score": 0.44771, "best_iter": 600, "best_epoch": 4, "TrainLoss": 12.183783531188965, "CAPTrainLoss": 6.477785587310791, "SVOTrainLoss": 4.754998207092285, "mixer_from": -1, "scb_captions": 0, "Loss": -4.167, "Bleu_1": 0.74521, "Bleu_2": 0.61041, "Bleu_3": 0.51202, "Bleu_4": 0.40614, "METEOR": 0.27636, "ROUGE_L": 0.6624, "CIDEr": 0.44771, "SPICE": 0.03275}, "5": {"iter": 750, "epoch": 5, "start_epoch": 0, "best_score": 0.44771, "best_iter": 600, "best_epoch": 4, "TrainLoss": 7.957524299621582, "CAPTrainLoss": 3.6245226860046387, "SVOTrainLoss": 3.6108343601226807, "mixer_from": -1, "scb_captions": 0, "Loss": -4.092, "Bleu_1": 0.73091, "Bleu_2": 0.58264, "Bleu_3": 0.48552, "Bleu_4": 0.37885, "METEOR": 0.2745, "ROUGE_L": 0.65979, "CIDEr": 0.38215, "SPICE": 0.03182}, "6": {"iter": 900, "epoch": 6, "start_epoch": 0, "best_score": 0.48807, "best_iter": 900, "best_epoch": 6, "TrainLoss": 11.34470272064209, "CAPTrainLoss": 6.159243106842041, "SVOTrainLoss": 4.321216106414795, "mixer_from": -1, "scb_captions": 0, "Loss": -4.085, "Bleu_1": 0.74802, "Bleu_2": 0.61908, "Bleu_3": 0.52837, "Bleu_4": 0.42472, "METEOR": 0.28237, "ROUGE_L": 0.66896, "CIDEr": 0.48807, "SPICE": 0.0321}, "7": {"iter": 1050, "epoch": 7, "start_epoch": 0, "best_score": 0.48807, "best_iter": 900, "best_epoch": 6, "TrainLoss": 8.668685913085938, "CAPTrainLoss": 4.290333271026611, "SVOTrainLoss": 3.6486265659332275, "mixer_from": -1, "scb_captions": 0, "Loss": -3.924, "Bleu_1": 0.7404, "Bleu_2": 0.59953, "Bleu_3": 0.50319, "Bleu_4": 0.39668, "METEOR": 0.27941, "ROUGE_L": 0.66171, "CIDEr": 0.47631, "SPICE": 0.03277}, "8": {"iter": 1200, "epoch": 8, "start_epoch": 0, "best_score": 0.56668, "best_iter": 1200, "best_epoch": 8, "TrainLoss": 10.404558181762695, "CAPTrainLoss": 5.5127668380737305, "SVOTrainLoss": 4.0764923095703125, "mixer_from": -1, "scb_captions": 0, "Loss": -3.97, "Bleu_1": 0.74368, "Bleu_2": 0.60844, "Bleu_3": 0.51551, "Bleu_4": 0.41501, "METEOR": 0.29059, "ROUGE_L": 0.66965, "CIDEr": 0.56668, "SPICE": 0.03462}, "9": {"iter": 1350, "epoch": 9, "start_epoch": 0, "best_score": 0.56668, "best_iter": 1200, "best_epoch": 8, "TrainLoss": 8.75826644897461, "CAPTrainLoss": 4.544933319091797, "SVOTrainLoss": 3.511110305786133, "mixer_from": -1, "scb_captions": 0, "Loss": -3.849, "Bleu_1": 0.7289, "Bleu_2": 0.58831, "Bleu_3": 0.48682, "Bleu_4": 0.38112, "METEOR": 0.27736, "ROUGE_L": 0.64429, "CIDEr": 0.46468, "SPICE": 0.03167}, "10": {"iter": 1500, "epoch": 10, "start_epoch": 0, "best_score": 0.58612, "best_iter": 1500, "best_epoch": 10, "TrainLoss": 8.81761646270752, "CAPTrainLoss": 4.751270771026611, "SVOTrainLoss": 3.3886210918426514, "mixer_from": -1, "scb_captions": 0, "Loss": -3.853, "Bleu_1": 0.75181, "Bleu_2": 0.6305, "Bleu_3": 0.53944, "Bleu_4": 0.43969, "METEOR": 0.30806, "ROUGE_L": 0.67425, "CIDEr": 0.58612, "SPICE": 0.03765}, "11": {"iter": 1650, "epoch": 11, "start_epoch": 0, "best_score": 0.58612, "best_iter": 1500, "best_epoch": 10, "TrainLoss": 8.239370346069336, "CAPTrainLoss": 4.040980815887451, "SVOTrainLoss": 3.4986581802368164, "mixer_from": -1, "scb_captions": 0, "Loss": -3.822, "Bleu_1": 0.74731, "Bleu_2": 0.61935, "Bleu_3": 0.51855, "Bleu_4": 0.40767, "METEOR": 0.29315, "ROUGE_L": 0.6658, "CIDEr": 0.54988, "SPICE": 0.03369}, "12": {"iter": 1800, "epoch": 12, "start_epoch": 0, "best_score": 0.58612, "best_iter": 1500, "best_epoch": 10, "TrainLoss": 8.808876991271973, "CAPTrainLoss": 4.24652099609375, "SVOTrainLoss": 3.8019630908966064, "mixer_from": -1, "scb_captions": 0, "Loss": -3.785, "Bleu_1": 0.74353, "Bleu_2": 0.60734, "Bleu_3": 0.50497, "Bleu_4": 0.39622, "METEOR": 0.28769, "ROUGE_L": 0.66231, "CIDEr": 0.55139, "SPICE": 0.0339}, "13": {"iter": 1950, "epoch": 13, "start_epoch": 0, "best_score": 0.58893, "best_iter": 1950, "best_epoch": 13, "TrainLoss": 8.241385459899902, "CAPTrainLoss": 3.7101120948791504, "SVOTrainLoss": 3.7760608196258545, "mixer_from": -1, "scb_captions": 0, "Loss": -3.724, "Bleu_1": 0.74047, "Bleu_2": 0.60373, "Bleu_3": 0.50361, "Bleu_4": 0.40715, "METEOR": 0.28707, "ROUGE_L": 0.65527, "CIDEr": 0.58893, "SPICE": 0.03535}, "14": {"iter": 2100, "epoch": 14, "start_epoch": 0, "best_score": 0.62062, "best_iter": 2100, "best_epoch": 14, "TrainLoss": 8.90280818939209, "CAPTrainLoss": 5.262490749359131, "SVOTrainLoss": 3.033597946166992, "mixer_from": -1, "scb_captions": 0, "Loss": -3.773, "Bleu_1": 0.74315, "Bleu_2": 0.61208, "Bleu_3": 0.51129, "Bleu_4": 0.40647, "METEOR": 0.30123, "ROUGE_L": 0.66157, "CIDEr": 0.62062, "SPICE": 0.03715}, "15": {"iter": 2250, "epoch": 15, "start_epoch": 0, "best_score": 0.62062, "best_iter": 2100, "best_epoch": 14, "TrainLoss": 8.678016662597656, "CAPTrainLoss": 4.762372016906738, "SVOTrainLoss": 3.2630367279052734, "mixer_from": -1, "scb_captions": 0, "Loss": -3.703, "Bleu_1": 0.75567, "Bleu_2": 0.62575, "Bleu_3": 0.52536, "Bleu_4": 0.41362, "METEOR": 0.29658, "ROUGE_L": 0.67275, "CIDEr": 0.59044, "SPICE": 0.03719}, "16": {"iter": 2400, "epoch": 16, "start_epoch": 0, "best_score": 0.66287, "best_iter": 2400, "best_epoch": 16, "TrainLoss": 8.33586311340332, "CAPTrainLoss": 3.750889539718628, "SVOTrainLoss": 3.8208110332489014, "mixer_from": -1, "scb_captions": 0, "Loss": -3.659, "Bleu_1": 0.73779, "Bleu_2": 0.6147, "Bleu_3": 0.52216, "Bleu_4": 0.41751, "METEOR": 0.29327, "ROUGE_L": 0.6692, "CIDEr": 0.66287, "SPICE": 0.03824}, "17": {"iter": 2550, "epoch": 17, "start_epoch": 0, "best_score": 0.66287, "best_iter": 2400, "best_epoch": 16, "TrainLoss": 7.588397026062012, "CAPTrainLoss": 3.519418954849243, "SVOTrainLoss": 3.390814781188965, "mixer_from": -1, "scb_captions": 0, "Loss": -3.73, "Bleu_1": 0.73321, "Bleu_2": 0.59257, "Bleu_3": 0.49346, "Bleu_4": 0.39188, "METEOR": 0.28557, "ROUGE_L": 0.66156, "CIDEr": 0.63038, "SPICE": 0.0358}, "18": {"iter": 2700, "epoch": 18, "start_epoch": 0, "best_score": 0.66287, "best_iter": 2400, "best_epoch": 16, "TrainLoss": 8.65772533416748, "CAPTrainLoss": 4.560891151428223, "SVOTrainLoss": 3.4140284061431885, "mixer_from": -1, "scb_captions": 0, "Loss": -3.642, "Bleu_1": 0.74137, "Bleu_2": 0.60396, "Bleu_3": 0.50002, "Bleu_4": 0.39258, "METEOR": 0.29287, "ROUGE_L": 0.66704, "CIDEr": 0.62473, "SPICE": 0.03745}, "19": {"iter": 2850, "epoch": 19, "start_epoch": 0, "best_score": 0.66287, "best_iter": 2400, "best_epoch": 16, "TrainLoss": 7.5476813316345215, "CAPTrainLoss": 3.6838510036468506, "SVOTrainLoss": 3.219858407974243, "mixer_from": -1, "scb_captions": 0, "Loss": -3.603, "Bleu_1": 0.75311, "Bleu_2": 0.6274, "Bleu_3": 0.53219, "Bleu_4": 0.42882, "METEOR": 0.30007, "ROUGE_L": 0.67074, "CIDEr": 0.64445, "SPICE": 0.03972}, "20": {"iter": 3000, "epoch": 20, "start_epoch": 0, "best_score": 0.66287, "best_iter": 2400, "best_epoch": 16, "TrainLoss": 8.520340919494629, "CAPTrainLoss": 4.775387287139893, "SVOTrainLoss": 3.1207945346832275, "mixer_from": -1, "scb_captions": 0, "Loss": -3.585, "Bleu_1": 0.73021, "Bleu_2": 0.60303, "Bleu_3": 0.50507, "Bleu_4": 0.40434, "METEOR": 0.29321, "ROUGE_L": 0.66511, "CIDEr": 0.6141, "SPICE": 0.03473}, "21": {"iter": 3150, "epoch": 21, "start_epoch": 0, "best_score": 0.66287, "best_iter": 2400, "best_epoch": 16, "TrainLoss": 8.870250701904297, "CAPTrainLoss": 5.20315408706665, "SVOTrainLoss": 3.0559141635894775, "mixer_from": -1, "scb_captions": 0, "Loss": -3.589, "Bleu_1": 0.73594, "Bleu_2": 0.59992, "Bleu_3": 0.49603, "Bleu_4": 0.39142, "METEOR": 0.29789, "ROUGE_L": 0.67092, "CIDEr": 0.6125, "SPICE": 0.03616}, "22": {"iter": 3300, "epoch": 22, "start_epoch": 0, "best_score": 0.66287, "best_iter": 2400, "best_epoch": 16, "TrainLoss": 6.709105491638184, "CAPTrainLoss": 3.1376678943634033, "SVOTrainLoss": 2.9761977195739746, "mixer_from": -1, "scb_captions": 0, "Loss": -3.589, "Bleu_1": 0.7439, "Bleu_2": 0.60741, "Bleu_3": 0.49922, "Bleu_4": 0.39218, "METEOR": 0.28911, "ROUGE_L": 0.66334, "CIDEr": 0.5767, "SPICE": 0.03672}, "23": {"iter": 3450, "epoch": 23, "start_epoch": 0, "best_score": 0.66287, "best_iter": 2400, "best_epoch": 16, "TrainLoss": 8.838252067565918, "CAPTrainLoss": 4.872735500335693, "SVOTrainLoss": 3.3045969009399414, "mixer_from": -1, "scb_captions": 0, "Loss": -3.55, "Bleu_1": 0.75174, "Bleu_2": 0.63956, "Bleu_3": 0.54279, "Bleu_4": 0.44053, "METEOR": 0.31694, "ROUGE_L": 0.68899, "CIDEr": 0.65878, "SPICE": 0.0416}, "24": {"iter": 3600, "epoch": 24, "start_epoch": 0, "best_score": 0.69077, "best_iter": 3600, "best_epoch": 24, "TrainLoss": 7.162212371826172, "CAPTrainLoss": 4.4332594871521, "SVOTrainLoss": 2.27412748336792, "mixer_from": -1, "scb_captions": 0, "Loss": -3.538, "Bleu_1": 0.75714, "Bleu_2": 0.64288, "Bleu_3": 0.54901, "Bleu_4": 0.44593, "METEOR": 0.31202, "ROUGE_L": 0.68775, "CIDEr": 0.69077, "SPICE": 0.03853}, "25": {"iter": 3750, "epoch": 25, "start_epoch": 0, "best_score": 0.69077, "best_iter": 3600, "best_epoch": 24, "TrainLoss": 9.315139770507812, "CAPTrainLoss": 5.486854076385498, "SVOTrainLoss": 3.190237522125244, "mixer_from": -1, "scb_captions": 0, "Loss": -3.507, "Bleu_1": 0.74346, "Bleu_2": 0.61802, "Bleu_3": 0.52086, "Bleu_4": 0.42663, "METEOR": 0.29873, "ROUGE_L": 0.66548, "CIDEr": 0.68946, "SPICE": 0.03799}, "26": {"iter": 3900, "epoch": 26, "start_epoch": 0, "best_score": 0.72692, "best_iter": 3900, "best_epoch": 26, "TrainLoss": 7.366265296936035, "CAPTrainLoss": 4.301074028015137, "SVOTrainLoss": 2.554326057434082, "mixer_from": -1, "scb_captions": 0, "Loss": -3.555, "Bleu_1": 0.74561, "Bleu_2": 0.62228, "Bleu_3": 0.52861, "Bleu_4": 0.43278, "METEOR": 0.31395, "ROUGE_L": 0.68749, "CIDEr": 0.72692, "SPICE": 0.03783}, "27": {"iter": 4050, "epoch": 27, "start_epoch": 0, "best_score": 0.72692, "best_iter": 3900, "best_epoch": 26, "TrainLoss": 7.4996724128723145, "CAPTrainLoss": 3.636442184448242, "SVOTrainLoss": 3.219358444213867, "mixer_from": -1, "scb_captions": 0, "Loss": -3.493, "Bleu_1": 0.74144, "Bleu_2": 0.61761, "Bleu_3": 0.51686, "Bleu_4": 0.41154, "METEOR": 0.31203, "ROUGE_L": 0.67956, "CIDEr": 0.67552, "SPICE": 0.03986}, "28": {"iter": 4200, "epoch": 28, "start_epoch": 0, "best_score": 0.72692, "best_iter": 3900, "best_epoch": 26, "TrainLoss": 7.545079708099365, "CAPTrainLoss": 4.096456527709961, "SVOTrainLoss": 2.873852491378784, "mixer_from": -1, "scb_captions": 0, "Loss": -3.466, "Bleu_1": 0.74868, "Bleu_2": 0.62154, "Bleu_3": 0.51831, "Bleu_4": 0.41445, "METEOR": 0.3012, "ROUGE_L": 0.66517, "CIDEr": 0.5965, "SPICE": 0.03778}, "29": {"iter": 4350, "epoch": 29, "start_epoch": 0, "best_score": 0.72692, "best_iter": 3900, "best_epoch": 26, "TrainLoss": 7.517395973205566, "CAPTrainLoss": 4.256125450134277, "SVOTrainLoss": 2.7177252769470215, "mixer_from": -1, "scb_captions": 0, "Loss": -3.426, "Bleu_1": 0.75223, "Bleu_2": 0.63497, "Bleu_3": 0.53763, "Bleu_4": 0.43497, "METEOR": 0.30912, "ROUGE_L": 0.68967, "CIDEr": 0.64268, "SPICE": 0.04088}, "30": {"iter": 4500, "epoch": 30, "start_epoch": 0, "best_score": 0.72692, "best_iter": 3900, "best_epoch": 26, "TrainLoss": 6.413482666015625, "CAPTrainLoss": 3.071007490158081, "SVOTrainLoss": 2.785396099090576, "mixer_from": -1, "scb_captions": 0, "Loss": -3.472, "Bleu_1": 0.74332, "Bleu_2": 0.62595, "Bleu_3": 0.52849, "Bleu_4": 0.42186, "METEOR": 0.313, "ROUGE_L": 0.67509, "CIDEr": 0.66955, "SPICE": 0.04155}, "31": {"iter": 4650, "epoch": 31, "start_epoch": 0, "best_score": 0.72692, "best_iter": 3900, "best_epoch": 26, "TrainLoss": 6.353070259094238, "CAPTrainLoss": 3.219027519226074, "SVOTrainLoss": 2.6117022037506104, "mixer_from": -1, "scb_captions": 0, "Loss": -3.479, "Bleu_1": 0.74523, "Bleu_2": 0.62121, "Bleu_3": 0.51954, "Bleu_4": 0.41216, "METEOR": 0.30447, "ROUGE_L": 0.67826, "CIDEr": 0.60718, "SPICE": 0.03914}, "32": {"iter": 4800, "epoch": 32, "start_epoch": 0, "best_score": 0.72692, "best_iter": 3900, "best_epoch": 26, "TrainLoss": 6.970178127288818, "CAPTrainLoss": 4.1785888671875, "SVOTrainLoss": 2.326324224472046, "mixer_from": -1, "scb_captions": 0, "Loss": -3.505, "Bleu_1": 0.7431, "Bleu_2": 0.62471, "Bleu_3": 0.53143, "Bleu_4": 0.43389, "METEOR": 0.31141, "ROUGE_L": 0.68008, "CIDEr": 0.67013, "SPICE": 0.04065}, "33": {"iter": 4950, "epoch": 33, "start_epoch": 0, "best_score": 0.72692, "best_iter": 3900, "best_epoch": 26, "TrainLoss": 7.944025039672852, "CAPTrainLoss": 3.8679919242858887, "SVOTrainLoss": 3.3966941833496094, "mixer_from": -1, "scb_captions": 0, "Loss": -3.498, "Bleu_1": 0.75179, "Bleu_2": 0.63148, "Bleu_3": 0.53469, "Bleu_4": 0.43338, "METEOR": 0.30982, "ROUGE_L": 0.67751, "CIDEr": 0.61375, "SPICE": 0.04062}, "34": {"iter": 5100, "epoch": 34, "start_epoch": 0, "best_score": 0.72692, "best_iter": 3900, "best_epoch": 26, "TrainLoss": 6.40523624420166, "CAPTrainLoss": 3.2702696323394775, "SVOTrainLoss": 2.6124722957611084, "mixer_from": -1, "scb_captions": 0, "Loss": -3.505, "Bleu_1": 0.74399, "Bleu_2": 0.6212, "Bleu_3": 0.5247, "Bleu_4": 0.42044, "METEOR": 0.30855, "ROUGE_L": 0.68018, "CIDEr": 0.6752, "SPICE": 0.04047}, "35": {"iter": 5250, "epoch": 35, "start_epoch": 0, "best_score": 0.72692, "best_iter": 3900, "best_epoch": 26, "TrainLoss": 6.967527866363525, "CAPTrainLoss": 4.1096086502075195, "SVOTrainLoss": 2.381599187850952, "mixer_from": -1, "scb_captions": 0, "Loss": -3.445, "Bleu_1": 0.7386, "Bleu_2": 0.61796, "Bleu_3": 0.52599, "Bleu_4": 0.42406, "METEOR": 0.30466, "ROUGE_L": 0.67716, "CIDEr": 0.5432, "SPICE": 0.03959}, "36": {"iter": 5400, "epoch": 36, "start_epoch": 0, "best_score": 0.72692, "best_iter": 3900, "best_epoch": 26, "TrainLoss": 6.720399379730225, "CAPTrainLoss": 3.9678187370300293, "SVOTrainLoss": 2.2938170433044434, "mixer_from": -1, "scb_captions": 0, "Loss": -3.518, "Bleu_1": 0.74609, "Bleu_2": 0.62664, "Bleu_3": 0.53102, "Bleu_4": 0.42691, "METEOR": 0.30769, "ROUGE_L": 0.67577, "CIDEr": 0.66598, "SPICE": 0.04161}, "37": {"iter": 5550, "epoch": 37, "start_epoch": 0, "best_score": 0.72692, "best_iter": 3900, "best_epoch": 26, "TrainLoss": 7.232823848724365, "CAPTrainLoss": 3.8191065788269043, "SVOTrainLoss": 2.844764232635498, "mixer_from": -1, "scb_captions": 0, "Loss": -3.471, "Bleu_1": 0.73739, "Bleu_2": 0.61188, "Bleu_3": 0.51681, "Bleu_4": 0.41698, "METEOR": 0.29402, "ROUGE_L": 0.66537, "CIDEr": 0.6297, "SPICE": 0.03943}, "38": {"iter": 5700, "epoch": 38, "start_epoch": 0, "best_score": 0.72692, "best_iter": 3900, "best_epoch": 26, "TrainLoss": 6.537203788757324, "CAPTrainLoss": 3.8590333461761475, "SVOTrainLoss": 2.2318084239959717, "mixer_from": -1, "scb_captions": 0, "Loss": -3.523, "Bleu_1": 0.73217, "Bleu_2": 0.59822, "Bleu_3": 0.49648, "Bleu_4": 0.3941, "METEOR": 0.28412, "ROUGE_L": 0.65391, "CIDEr": 0.58149, "SPICE": 0.03848}, "39": {"iter": 5850, "epoch": 39, "start_epoch": 0, "best_score": 0.72692, "best_iter": 3900, "best_epoch": 26, "TrainLoss": 6.682098388671875, "CAPTrainLoss": 3.7657480239868164, "SVOTrainLoss": 2.4302921295166016, "mixer_from": -1, "scb_captions": 0, "Loss": -3.471, "Bleu_1": 0.75169, "Bleu_2": 0.63268, "Bleu_3": 0.54209, "Bleu_4": 0.44975, "METEOR": 0.31397, "ROUGE_L": 0.68574, "CIDEr": 0.63237, "SPICE": 0.04243}, "40": {"iter": 6000, "epoch": 40, "start_epoch": 0, "best_score": 0.72692, "best_iter": 3900, "best_epoch": 26, "TrainLoss": 6.173464775085449, "CAPTrainLoss": 3.1501779556274414, "SVOTrainLoss": 2.5194056034088135, "mixer_from": -1, "scb_captions": 0, "Loss": -3.526, "Bleu_1": 0.72759, "Bleu_2": 0.59045, "Bleu_3": 0.496, "Bleu_4": 0.40212, "METEOR": 0.28232, "ROUGE_L": 0.65132, "CIDEr": 0.55012, "SPICE": 0.03694}, "41": {"iter": 6150, "epoch": 41, "start_epoch": 0, "best_score": 0.72692, "best_iter": 3900, "best_epoch": 26, "TrainLoss": 7.815613746643066, "CAPTrainLoss": 4.305321216583252, "SVOTrainLoss": 2.925243377685547, "mixer_from": -1, "scb_captions": 0, "Loss": -3.51, "Bleu_1": 0.72852, "Bleu_2": 0.60365, "Bleu_3": 0.51492, "Bleu_4": 0.42772, "METEOR": 0.28944, "ROUGE_L": 0.65524, "CIDEr": 0.66593, "SPICE": 0.041}, "42": {"iter": 6300, "epoch": 42, "start_epoch": 0, "best_score": 0.72692, "best_iter": 3900, "best_epoch": 26, "TrainLoss": 7.3707275390625, "CAPTrainLoss": 4.702462196350098, "SVOTrainLoss": 2.2235546112060547, "mixer_from": -1, "scb_captions": 0, "Loss": -3.418, "Bleu_1": 0.75176, "Bleu_2": 0.6337, "Bleu_3": 0.54088, "Bleu_4": 0.44926, "METEOR": 0.31635, "ROUGE_L": 0.687, "CIDEr": 0.68914, "SPICE": 0.03982}, "43": {"iter": 6450, "epoch": 43, "start_epoch": 0, "best_score": 0.72692, "best_iter": 3900, "best_epoch": 26, "TrainLoss": 6.974783420562744, "CAPTrainLoss": 3.9737954139709473, "SVOTrainLoss": 2.5008232593536377, "mixer_from": -1, "scb_captions": 0, "Loss": -3.499, "Bleu_1": 0.75047, "Bleu_2": 0.63931, "Bleu_3": 0.55767, "Bleu_4": 0.47574, "METEOR": 0.30414, "ROUGE_L": 0.67376, "CIDEr": 0.62844, "SPICE": 0.04178}, "44": {"iter": 6600, "epoch": 44, "start_epoch": 0, "best_score": 0.72692, "best_iter": 3900, "best_epoch": 26, "TrainLoss": 7.194668769836426, "CAPTrainLoss": 4.837157249450684, "SVOTrainLoss": 1.964592695236206, "mixer_from": -1, "scb_captions": 0, "Loss": -3.451, "Bleu_1": 0.73721, "Bleu_2": 0.61564, "Bleu_3": 0.53242, "Bleu_4": 0.44622, "METEOR": 0.29316, "ROUGE_L": 0.66279, "CIDEr": 0.66787, "SPICE": 0.03983}, "45": {"iter": 6750, "epoch": 45, "start_epoch": 0, "best_score": 0.72692, "best_iter": 3900, "best_epoch": 26, "TrainLoss": 6.631608486175537, "CAPTrainLoss": 3.843529224395752, "SVOTrainLoss": 2.323399305343628, "mixer_from": -1, "scb_captions": 0, "Loss": -3.45, "Bleu_1": 0.72402, "Bleu_2": 0.60105, "Bleu_3": 0.51107, "Bleu_4": 0.42478, "METEOR": 0.28793, "ROUGE_L": 0.66259, "CIDEr": 0.60858, "SPICE": 0.03931}, "46": {"iter": 6900, "epoch": 46, "start_epoch": 0, "best_score": 0.72692, "best_iter": 3900, "best_epoch": 26, "TrainLoss": 6.031429290771484, "CAPTrainLoss": 3.4161436557769775, "SVOTrainLoss": 2.1794044971466064, "mixer_from": -1, "scb_captions": 0, "Loss": -3.486, "Bleu_1": 0.73519, "Bleu_2": 0.61034, "Bleu_3": 0.51889, "Bleu_4": 0.42035, "METEOR": 0.29435, "ROUGE_L": 0.66396, "CIDEr": 0.63159, "SPICE": 0.03851}, "47": {"iter": 7050, "epoch": 47, "start_epoch": 0, "best_score": 0.72692, "best_iter": 3900, "best_epoch": 26, "TrainLoss": 7.155804634094238, "CAPTrainLoss": 3.9234941005706787, "SVOTrainLoss": 2.693591833114624, "mixer_from": -1, "scb_captions": 0, "Loss": -3.445, "Bleu_1": 0.7268, "Bleu_2": 0.6009, "Bleu_3": 0.50838, "Bleu_4": 0.41639, "METEOR": 0.29911, "ROUGE_L": 0.66052, "CIDEr": 0.56543, "SPICE": 0.03819}, "48": {"iter": 7200, "epoch": 48, "start_epoch": 0, "best_score": 0.72692, "best_iter": 3900, "best_epoch": 26, "TrainLoss": 7.271419525146484, "CAPTrainLoss": 4.187631130218506, "SVOTrainLoss": 2.5698235034942627, "mixer_from": -1, "scb_captions": 0, "Loss": -3.378, "Bleu_1": 0.73322, "Bleu_2": 0.60937, "Bleu_3": 0.51926, "Bleu_4": 0.4233, "METEOR": 0.29466, "ROUGE_L": 0.66108, "CIDEr": 0.61501, "SPICE": 0.04131}, "49": {"iter": 7350, "epoch": 49, "start_epoch": 0, "best_score": 0.72692, "best_iter": 3900, "best_epoch": 26, "TrainLoss": 5.537438869476318, "CAPTrainLoss": 3.0493338108062744, "SVOTrainLoss": 2.073420763015747, "mixer_from": -1, "scb_captions": 0, "Loss": -3.387, "Bleu_1": 0.7386, "Bleu_2": 0.61541, "Bleu_3": 0.5233, "Bleu_4": 0.42762, "METEOR": 0.30032, "ROUGE_L": 0.67666, "CIDEr": 0.67025, "SPICE": 0.04197}, "50": {"iter": 7500, "epoch": 50, "start_epoch": 0, "best_score": 0.72692, "best_iter": 3900, "best_epoch": 26, "TrainLoss": 5.525120735168457, "CAPTrainLoss": 2.9473979473114014, "SVOTrainLoss": 2.148102283477783, "mixer_from": -1, "scb_captions": 0, "Loss": -3.45, "Bleu_1": 0.74695, "Bleu_2": 0.62328, "Bleu_3": 0.5313, "Bleu_4": 0.4347, "METEOR": 0.30029, "ROUGE_L": 0.67098, "CIDEr": 0.6158, "SPICE": 0.04197}, "51": {"iter": 7650, "epoch": 51, "start_epoch": 0, "best_score": 0.72692, "best_iter": 3900, "best_epoch": 26, "TrainLoss": 7.104500770568848, "CAPTrainLoss": 4.402806758880615, "SVOTrainLoss": 2.2514114379882812, "mixer_from": -1, "scb_captions": 0, "Loss": -3.426, "Bleu_1": 0.73693, "Bleu_2": 0.61338, "Bleu_3": 0.52028, "Bleu_4": 0.42588, "METEOR": 0.30715, "ROUGE_L": 0.67359, "CIDEr": 0.67599, "SPICE": 0.04231}, "52": {"iter": 7800, "epoch": 52, "start_epoch": 0, "best_score": 0.72692, "best_iter": 3900, "best_epoch": 26, "TrainLoss": 7.086645126342773, "CAPTrainLoss": 4.181056499481201, "SVOTrainLoss": 2.4213240146636963, "mixer_from": -1, "scb_captions": 0, "Loss": -3.373, "Bleu_1": 0.71799, "Bleu_2": 0.5866, "Bleu_3": 0.49486, "Bleu_4": 0.404, "METEOR": 0.28541, "ROUGE_L": 0.64599, "CIDEr": 0.606, "SPICE": 0.03874}, "53": {"iter": 7950, "epoch": 53, "start_epoch": 0, "best_score": 0.72692, "best_iter": 3900, "best_epoch": 26, "TrainLoss": 6.000950813293457, "CAPTrainLoss": 3.2568657398223877, "SVOTrainLoss": 2.2867376804351807, "mixer_from": -1, "scb_captions": 0, "Loss": -3.375, "Bleu_1": 0.75302, "Bleu_2": 0.63066, "Bleu_3": 0.53874, "Bleu_4": 0.44974, "METEOR": 0.31002, "ROUGE_L": 0.67523, "CIDEr": 0.69337, "SPICE": 0.04518}, "54": {"iter": 8100, "epoch": 54, "start_epoch": 0, "best_score": 0.72692, "best_iter": 3900, "best_epoch": 26, "TrainLoss": 6.763312339782715, "CAPTrainLoss": 4.296633243560791, "SVOTrainLoss": 2.055565595626831, "mixer_from": -1, "scb_captions": 0, "Loss": -3.452, "Bleu_1": 0.71605, "Bleu_2": 0.59256, "Bleu_3": 0.51043, "Bleu_4": 0.42741, "METEOR": 0.28006, "ROUGE_L": 0.63686, "CIDEr": 0.60401, "SPICE": 0.03892}, "55": {"iter": 8250, "epoch": 55, "start_epoch": 0, "best_score": 0.72692, "best_iter": 3900, "best_epoch": 26, "TrainLoss": 5.862408638000488, "CAPTrainLoss": 3.286999464035034, "SVOTrainLoss": 2.146174192428589, "mixer_from": -1, "scb_captions": 0, "Loss": -3.339, "Bleu_1": 0.753, "Bleu_2": 0.62928, "Bleu_3": 0.53487, "Bleu_4": 0.44108, "METEOR": 0.30086, "ROUGE_L": 0.67222, "CIDEr": 0.60871, "SPICE": 0.04327}, "56": {"iter": 8400, "epoch": 56, "start_epoch": 0, "best_score": 0.72692, "best_iter": 3900, "best_epoch": 26, "TrainLoss": 6.0174560546875, "CAPTrainLoss": 3.553943634033203, "SVOTrainLoss": 2.052926778793335, "mixer_from": -1, "scb_captions": 0, "Loss": -3.409, "Bleu_1": 0.7309, "Bleu_2": 0.60325, "Bleu_3": 0.50744, "Bleu_4": 0.40881, "METEOR": 0.2896, "ROUGE_L": 0.65406, "CIDEr": 0.62905, "SPICE": 0.04047}, "57": {"iter": 8550, "epoch": 57, "start_epoch": 0, "best_score": 0.72692, "best_iter": 3900, "best_epoch": 26, "TrainLoss": 5.447902202606201, "CAPTrainLoss": 3.2724320888519287, "SVOTrainLoss": 1.8128916025161743, "mixer_from": -1, "scb_captions": 0, "Loss": -3.408, "Bleu_1": 0.73765, "Bleu_2": 0.61166, "Bleu_3": 0.51947, "Bleu_4": 0.43153, "METEOR": 0.30732, "ROUGE_L": 0.66514, "CIDEr": 0.70971, "SPICE": 0.04313}, "58": {"iter": 8700, "epoch": 58, "start_epoch": 0, "best_score": 0.72692, "best_iter": 3900, "best_epoch": 26, "TrainLoss": 5.513096809387207, "CAPTrainLoss": 3.124115467071533, "SVOTrainLoss": 1.990817666053772, "mixer_from": -1, "scb_captions": 0, "Loss": -3.355, "Bleu_1": 0.74106, "Bleu_2": 0.61678, "Bleu_3": 0.5283, "Bleu_4": 0.44157, "METEOR": 0.30803, "ROUGE_L": 0.67177, "CIDEr": 0.61537, "SPICE": 0.04081}, "59": {"iter": 8850, "epoch": 59, "start_epoch": 0, "best_score": 0.72692, "best_iter": 3900, "best_epoch": 26, "TrainLoss": 6.508062362670898, "CAPTrainLoss": 3.947357416152954, "SVOTrainLoss": 2.133920669555664, "mixer_from": -1, "scb_captions": 0, "Loss": -3.4, "Bleu_1": 0.74003, "Bleu_2": 0.62029, "Bleu_3": 0.53015, "Bleu_4": 0.43408, "METEOR": 0.29375, "ROUGE_L": 0.66743, "CIDEr": 0.64565, "SPICE": 0.04319}, "60": {"iter": 9000, "epoch": 60, "start_epoch": 0, "best_score": 0.72692, "best_iter": 3900, "best_epoch": 26, "TrainLoss": 6.434835433959961, "CAPTrainLoss": 3.5588526725769043, "SVOTrainLoss": 2.3966519832611084, "mixer_from": -1, "scb_captions": 0, "Loss": -3.363, "Bleu_1": 0.71853, "Bleu_2": 0.58655, "Bleu_3": 0.49229, "Bleu_4": 0.40108, "METEOR": 0.2801, "ROUGE_L": 0.64402, "CIDEr": 0.64005, "SPICE": 0.04026}, "61": {"iter": 9150, "epoch": 61, "start_epoch": 0, "best_score": 0.72692, "best_iter": 3900, "best_epoch": 26, "TrainLoss": 5.714679718017578, "CAPTrainLoss": 3.342167854309082, "SVOTrainLoss": 1.97709321975708, "mixer_from": -1, "scb_captions": 0, "Loss": -3.328, "Bleu_1": 0.73286, "Bleu_2": 0.62, "Bleu_3": 0.53257, "Bleu_4": 0.44841, "METEOR": 0.30136, "ROUGE_L": 0.64693, "CIDEr": 0.65798, "SPICE": 0.04378}, "62": {"iter": 9300, "epoch": 62, "start_epoch": 0, "best_score": 0.72692, "best_iter": 3900, "best_epoch": 26, "TrainLoss": 5.4643425941467285, "CAPTrainLoss": 3.7760848999023438, "SVOTrainLoss": 1.4068814516067505, "mixer_from": -1, "scb_captions": 0, "Loss": -3.409, "Bleu_1": 0.72696, "Bleu_2": 0.59458, "Bleu_3": 0.49544, "Bleu_4": 0.38942, "METEOR": 0.28931, "ROUGE_L": 0.65544, "CIDEr": 0.51548, "SPICE": 0.04039}, "63": {"iter": 9450, "epoch": 63, "start_epoch": 0, "best_score": 0.72692, "best_iter": 3900, "best_epoch": 26, "TrainLoss": 5.973525047302246, "CAPTrainLoss": 3.5743117332458496, "SVOTrainLoss": 1.9993444681167603, "mixer_from": -1, "scb_captions": 0, "Loss": -3.38, "Bleu_1": 0.73621, "Bleu_2": 0.60418, "Bleu_3": 0.51112, "Bleu_4": 0.4196, "METEOR": 0.29386, "ROUGE_L": 0.65798, "CIDEr": 0.59731, "SPICE": 0.04255}, "64": {"iter": 9600, "epoch": 64, "start_epoch": 0, "best_score": 0.72692, "best_iter": 3900, "best_epoch": 26, "TrainLoss": 5.633817195892334, "CAPTrainLoss": 3.2271909713745117, "SVOTrainLoss": 2.005521774291992, "mixer_from": -1, "scb_captions": 0, "Loss": -3.284, "Bleu_1": 0.71404, "Bleu_2": 0.59688, "Bleu_3": 0.50834, "Bleu_4": 0.41575, "METEOR": 0.2955, "ROUGE_L": 0.64555, "CIDEr": 0.60087, "SPICE": 0.04072}, "65": {"iter": 9750, "epoch": 65, "start_epoch": 0, "best_score": 0.72692, "best_iter": 3900, "best_epoch": 26, "TrainLoss": 6.098235130310059, "CAPTrainLoss": 3.86993408203125, "SVOTrainLoss": 1.856917381286621, "mixer_from": -1, "scb_captions": 0, "Loss": -3.416, "Bleu_1": 0.73356, "Bleu_2": 0.60254, "Bleu_3": 0.50811, "Bleu_4": 0.40818, "METEOR": 0.2998, "ROUGE_L": 0.67283, "CIDEr": 0.62373, "SPICE": 0.04134}, "66": {"iter": 9900, "epoch": 66, "start_epoch": 0, "best_score": 0.72692, "best_iter": 3900, "best_epoch": 26, "TrainLoss": 5.862910747528076, "CAPTrainLoss": 3.6048314571380615, "SVOTrainLoss": 1.8817325830459595, "mixer_from": -1, "scb_captions": 0, "Loss": -3.379, "Bleu_1": 0.72774, "Bleu_2": 0.59189, "Bleu_3": 0.49006, "Bleu_4": 0.3903, "METEOR": 0.28786, "ROUGE_L": 0.65724, "CIDEr": 0.57959, "SPICE": 0.04151}, "67": {"iter": 10050, "epoch": 67, "start_epoch": 0, "best_score": 0.72692, "best_iter": 3900, "best_epoch": 26, "TrainLoss": 5.915471076965332, "CAPTrainLoss": 3.2294085025787354, "SVOTrainLoss": 2.2383856773376465, "mixer_from": -1, "scb_captions": 0, "Loss": -3.398, "Bleu_1": 0.72837, "Bleu_2": 0.59329, "Bleu_3": 0.48696, "Bleu_4": 0.3815, "METEOR": 0.28614, "ROUGE_L": 0.6529, "CIDEr": 0.57745, "SPICE": 0.04151}, "68": {"iter": 10200, "epoch": 68, "start_epoch": 0, "best_score": 0.72692, "best_iter": 3900, "best_epoch": 26, "TrainLoss": 6.061460494995117, "CAPTrainLoss": 4.074615478515625, "SVOTrainLoss": 1.6557042598724365, "mixer_from": -1, "scb_captions": 0, "Loss": -3.347, "Bleu_1": 0.75722, "Bleu_2": 0.63817, "Bleu_3": 0.54778, "Bleu_4": 0.45597, "METEOR": 0.31541, "ROUGE_L": 0.68755, "CIDEr": 0.67652, "SPICE": 0.04653}, "69": {"iter": 10350, "epoch": 69, "start_epoch": 0, "best_score": 0.72692, "best_iter": 3900, "best_epoch": 26, "TrainLoss": 5.496988773345947, "CAPTrainLoss": 3.1736016273498535, "SVOTrainLoss": 1.936155915260315, "mixer_from": -1, "scb_captions": 0, "Loss": -3.346, "Bleu_1": 0.72496, "Bleu_2": 0.59025, "Bleu_3": 0.48955, "Bleu_4": 0.39506, "METEOR": 0.2922, "ROUGE_L": 0.64373, "CIDEr": 0.55691, "SPICE": 0.04154}, "70": {"iter": 10500, "epoch": 70, "start_epoch": 0, "best_score": 0.72692, "best_iter": 3900, "best_epoch": 26, "TrainLoss": 6.501562118530273, "CAPTrainLoss": 4.630465507507324, "SVOTrainLoss": 1.5592470169067383, "mixer_from": -1, "scb_captions": 0, "Loss": -3.408, "Bleu_1": 0.7242, "Bleu_2": 0.59248, "Bleu_3": 0.49366, "Bleu_4": 0.3985, "METEOR": 0.29322, "ROUGE_L": 0.6544, "CIDEr": 0.65779, "SPICE": 0.04072}, "71": {"iter": 10650, "epoch": 71, "start_epoch": 0, "best_score": 0.72692, "best_iter": 3900, "best_epoch": 26, "TrainLoss": 6.115602493286133, "CAPTrainLoss": 3.7251195907592773, "SVOTrainLoss": 1.9920690059661865, "mixer_from": -1, "scb_captions": 0, "Loss": -3.353, "Bleu_1": 0.73702, "Bleu_2": 0.60399, "Bleu_3": 0.51309, "Bleu_4": 0.42832, "METEOR": 0.30493, "ROUGE_L": 0.67125, "CIDEr": 0.65322, "SPICE": 0.04309}, "72": {"iter": 10800, "epoch": 72, "start_epoch": 0, "best_score": 0.72692, "best_iter": 3900, "best_epoch": 26, "TrainLoss": 6.1396484375, "CAPTrainLoss": 3.908839702606201, "SVOTrainLoss": 1.8590072393417358, "mixer_from": -1, "scb_captions": 0, "Loss": -3.327, "Bleu_1": 0.73862, "Bleu_2": 0.60586, "Bleu_3": 0.50514, "Bleu_4": 0.40638, "METEOR": 0.3014, "ROUGE_L": 0.66063, "CIDEr": 0.53268, "SPICE": 0.04065}, "73": {"iter": 10950, "epoch": 73, "start_epoch": 0, "best_score": 0.72692, "best_iter": 3900, "best_epoch": 26, "TrainLoss": 5.902427673339844, "CAPTrainLoss": 3.7289583683013916, "SVOTrainLoss": 1.811224102973938, "mixer_from": -1, "scb_captions": 0, "Loss": -3.328, "Bleu_1": 0.72804, "Bleu_2": 0.59965, "Bleu_3": 0.50691, "Bleu_4": 0.41265, "METEOR": 0.2988, "ROUGE_L": 0.65553, "CIDEr": 0.56704, "SPICE": 0.04313}, "74": {"iter": 11100, "epoch": 74, "start_epoch": 0, "best_score": 0.72692, "best_iter": 3900, "best_epoch": 26, "TrainLoss": 5.816103458404541, "CAPTrainLoss": 3.8383843898773193, "SVOTrainLoss": 1.6480990648269653, "mixer_from": -1, "scb_captions": 0, "Loss": -3.411, "Bleu_1": 0.73077, "Bleu_2": 0.6019, "Bleu_3": 0.51223, "Bleu_4": 0.42655, "METEOR": 0.29585, "ROUGE_L": 0.65265, "CIDEr": 0.58607, "SPICE": 0.04061}, "75": {"iter": 11250, "epoch": 75, "start_epoch": 0, "best_score": 0.72692, "best_iter": 3900, "best_epoch": 26, "TrainLoss": 6.299675941467285, "CAPTrainLoss": 4.008782863616943, "SVOTrainLoss": 1.909077525138855, "mixer_from": -1, "scb_captions": 0, "Loss": -3.358, "Bleu_1": 0.71972, "Bleu_2": 0.57816, "Bleu_3": 0.47864, "Bleu_4": 0.38203, "METEOR": 0.27984, "ROUGE_L": 0.64639, "CIDEr": 0.5945, "SPICE": 0.03953}, "76": {"iter": 11400, "epoch": 76, "start_epoch": 0, "best_score": 0.72692, "best_iter": 3900, "best_epoch": 26, "TrainLoss": 5.676886081695557, "CAPTrainLoss": 3.387692928314209, "SVOTrainLoss": 1.907660961151123, "mixer_from": -1, "scb_captions": 0, "Loss": -3.338, "Bleu_1": 0.72156, "Bleu_2": 0.58761, "Bleu_3": 0.49179, "Bleu_4": 0.39641, "METEOR": 0.29063, "ROUGE_L": 0.64879, "CIDEr": 0.53554, "SPICE": 0.04137}, "77": {"iter": 11550, "epoch": 77, "start_epoch": 0, "best_score": 0.72692, "best_iter": 3900, "best_epoch": 26, "TrainLoss": 5.092825889587402, "CAPTrainLoss": 2.861220359802246, "SVOTrainLoss": 1.8596712350845337, "mixer_from": -1, "scb_captions": 0, "Loss": -3.358, "Bleu_1": 0.73973, "Bleu_2": 0.61192, "Bleu_3": 0.52097, "Bleu_4": 0.42576, "METEOR": 0.29579, "ROUGE_L": 0.66423, "CIDEr": 0.61794, "SPICE": 0.0424}}